djangoappgen/__init__.py
djangoappgen/cli.py
djangoappgen/generator.py
djangoappgen/run.py
djangoappgen-0.1.1.dist-info/licenses/LICENSE
djangoappgen-0.1.1.dist-info/METADATA
djangoappgen-0.1.1.dist-info/WHEEL
djangoappgen-0.1.1.dist-info/entry_points.txt
djangoappgen-0.1.1.dist-info/top_level.txt
djangoappgen-0.1.1.dist-info/RECORD
