Metadata-Version: 2.4
Name: djangoappgen
Version: 0.1.1
Summary: Un générateur automatique d’applications Django
Author: Digital Dreamer
Author-email: Digital Dreammer <digitaldreamer@gmail.com>
License: MIT
Keywords: django,codegen,starter,app generator
Classifier: Programming Language :: Python :: 3
Classifier: Framework :: Django
Classifier: License :: OSI Approved :: MIT License
Classifier: Operating System :: OS Independent
Requires-Python: >=3.7
License-File: LICENSE
Dynamic: license-file
